nbstore/__init__.py
nbstore/formatter.py
nbstore/markdown.py
nbstore/notebook.py
nbstore/py.typed
nbstore/python.py
nbstore/store.py
nbstore-0.5.5.dist-info/WHEEL
nbstore-0.5.5.dist-info/METADATA
nbstore-0.5.5.dist-info/RECORD
