Metadata-Version: 2.3
Name: nbstore
Version: 0.5.5
Summary: A lightweight tool for extracting and manipulating content from Jupyter notebooks
Keywords: jupyter,notebook,extraction,content-management,visualization,markdown,documentation
Author: daizutabi
Author-email: daizutabi <daizutabi@gmail.com>
License: MIT License
Classifier: Development Status :: 4 - Beta
Classifier: Programming Language :: Python
Classifier: Programming Language :: Python :: 3.10
Classifier: Programming Language :: Python :: 3.11
Classifier: Programming Language :: Python :: 3.12
Classifier: Programming Language :: Python :: 3.13
Classifier: Programming Language :: Python :: 3.14
Classifier: Topic :: Documentation
Classifier: Topic :: Software Development :: Documentation
Classifier: Topic :: Text Processing :: Markup :: Markdown
Requires-Dist: nbformat>=5
Requires-Python: >=3.10
Project-URL: Documentation, https://daizutabi.github.io/nbstore/
Project-URL: Issues, https://github.com/daizutabi/nbstore/issues
Project-URL: Source, https://github.com/daizutabi/nbstore
